ashares/Ashare.py
ashares/__init__.py
ashares-1.1.dist-info/LICENSE
ashares-1.1.dist-info/METADATA
ashares-1.1.dist-info/WHEEL
ashares-1.1.dist-info/top_level.txt
ashares-1.1.dist-info/RECORD
