Metadata-Version: 2.1
Name: ashares
Version: 1.1
Summary: 简易A股行情数据API接口
Home-page: https://github.com/hidadeng/ashares
Author: 大邓
Author-email: thunderhit@qq.com
License: MIT
Keywords: chinese A stock market
Platform: UNKNOWN
Requires-Python: >=3.5
License-File: LICENSE
Requires-Dist: requests
Requires-Dist: pandas
